Workbook

Sheet Overview
A1: Overview
A3: COMPLETED SALES, GBP - excludes cancellations and negative adjustments; not net revenue or profit. Snapshot: 01 Dec 2010 to 09 Dec 2011.
A6: Metric | B6: Workbook value | C6: Python reference | D6: Reconciliation
A7: Completed-sales revenue GBP | B7: =ROUND(SUM('Monthly Sales'!B6:B18),2) -> 10247219 | C7: 10247219 | D7: =IF(ROUND(B7-C7,2)=0,"PASS","CHECK") -> PASS
A8: Distinct completed orders | B8: =SUM('Monthly Sales'!C6:C18) -> 19773 | C8: 19773 | D8: =IF(ROUND(B8-C8,2)=0,"PASS","CHECK") -> PASS
A9: Units sold | B9: =Sources!$B$22 -> 5561387 | C9: 5561387 | D9: =IF(ROUND(B9-C9,2)=0,"PASS","CHECK") -> PASS
A10: Average order value GBP | B10: =ROUND(B7/B8,2) -> 518.24 | C10: 518.24 | D10: =IF(ROUND(B10-C10,2)=0,"PASS","CHECK") -> PASS
A11: Known unique customers | B11: ='Customer Analysis'!B7 -> 4334 | C11: 4334 | D11: =IF(ROUND(B11-C11,2)=0,"PASS","CHECK") -> PASS
A12: Repeat customers | B12: ='Customer Analysis'!B8 -> 2829 | C12: 2829 | D12: =IF(ROUND(B12-C12,2)=0,"PASS","CHECK") -> PASS
A13: Repeat-customer rate | B13: ='Customer Analysis'!B10 -> 0.65274573 | C13: 0.6527 | D13: =IF(ROUND(B13*100,2)=ROUND(C13*100,2),"PASS","CHECK") -> PASS
A16: Metric definitions
A17: Revenue: Sum of eligible line-rounded integer pence / 100. Per line: Quantity x UnitPrice, ROUND_HALF_UP to GBP 0.01.
A18: Completed order: Distinct InvoiceNo containing eligible merchandise; an invoice can have multiple product lines.
A19: Units / AOV: Units = sum of eligible Quantity. AOV = completed-sales revenue / distinct completed orders.
A20: Known customer: Distinct nonmissing CustomerID with eligible sales. Anonymous sales remain in overall revenue and orders.
A21: Repeat rate: Known IDs with at least two distinct completed invoices / all known IDs with eligible sales. Denominator = 4,334.
A22: Monthly change: Observed MoM is a diagnostic. Comparable MoM excludes boundary pairs; December 2011 is partial.
A23: Product / country: Products group by exact StockCode; no inferred categories. Country is the observed source label.
A26: Business questions and scope
A27: How much eligible merchandise was sold, through how many orders, and at what average value?
A28: Which products and markets lead sales, and how do calendar-covered monthly totals vary?
A29: How many known customers return within the observed window, and how do data-quality decisions affect interpretation?
... A34: Evidence: all seven MariaDB 10.4.32 result tables matched Python. This workbook reconciles the same outputs; no cleaning or metric definitions were changed.

Sheet Monthly Sales
A1: Monthly Sales
I2: Native PivotTable: monthly summary
A3: Completed-sales revenue is GBP, not net revenue. Dec 2011 is partial through 9 Dec; Dec 2010 is a boundary with completeness unverified.
A5: Month | B5: Revenue GBP | C5: Completed orders | D5: AOV GBP | E5: Observed MoM % | F5: Comparable MoM % | G5: Coverage note | I5: Month | J5: Revenue GBP (sum) | K5: Completed orders (sum)
A6: 40513 | B6: 775638.36 | C6: 1550 | D6: =ROUND(B6/C6,2) -> 500.41 | G6: BOUNDARY - starts day 1; completeness unverified | I6: 40513 | J6: 775638.36 | K6: 1550
A7: 40544 | B7: 670380.24 | C7: 1081 | D7: =ROUND(B7/C7,2) -> 620.15 | E7: =IFERROR(B7/B6-1,"") -> -0.13570515 | F7: =IF(AND(G7="Interior calendar month",G6="Interior calendar month"),E7,"") | G7: Interior calendar month | I7: 40544 | J7: 670380.24 | K7: 1081
A8: 40575 | B8: 507799.87 | C8: 1093 | D8: =ROUND(B8/C8,2) -> 464.59 | E8: =IFERROR(B8/B7-1,"") -> -0.24251963 | F8: =IF(AND(G8="Interior calendar month",G7="Interior calendar month"),E8,"") -> -0.24251963 | G8: Interior calendar month | I8: 40575 | J8: 507799.87 | K8: 1093
A9: 40603 | B9: 689833.51 | C9: 1440 | D9: =ROUND(B9/C9,2) -> 479.05 | E9: =IFERROR(B9/B8-1,"") -> 0.35847516 | F9: =IF(AND(G9="Interior calendar month",G8="Interior calendar month"),E9,"") -> 0.35847516 | G9: Interior calendar month | I9: 40603 | J9: 689833.51 | K9: 1440
A10: 40634 | B10: 515377.99 | C10: 1235 | D10: =ROUND(B10/C10,2) -> 417.31 | E10: =IFERROR(B10/B9-1,"") -> -0.25289511 | F10: =IF(AND(G10="Interior calendar month",G9="Interior calendar month"),E10,"") -> -0.25289511 | G10: Interior calendar month | I10: 40634 | J10: 515377.99 | K10: 1235
A11: 40664 | B11: 739953 | C11: 1668 | D11: =ROUND(B11/C11,2) -> 443.62 | E11: =IFERROR(B11/B10-1,"") -> 0.43574816 | F11: =IF(AND(G11="Interior calendar month",G10="Interior calendar month"),E11,"") -> 0.43574816 | G11: Interior calendar month | I11: 40664 | J11: 739953 | K11: 1668
A12: 40695 | B12: 737558.98 | C12: 1525 | D12: =ROUND(B12/C12,2) -> 483.65 | E12: =IFERROR(B12/B11-1,"") -> -0.0032353677 | F12: =IF(AND(G12="Interior calendar month",G11="Interior calendar month"),E12,"") -> -0.0032353677 | G12: Interior calendar month | I12: 40695 | J12: 737558.98 | K12: 1525
A13: 40725 | B13: 688219.34 | C13: 1452 | D13: =ROUND(B13/C13,2) -> 473.98 | E13: =IFERROR(B13/B12-1,"") -> -0.066895857 | F13: =IF(AND(G13="Interior calendar month",G12="Interior calendar month"),E13,"") -> -0.066895857 | G13: Interior calendar month | I13: 40725 | J13: 688219.34 | K13: 1452
A14: 40756 | B14: 724216.5 | C14: 1339 | D14: =ROUND(B14/C14,2) -> 540.86 | E14: =IFERROR(B14/B13-1,"") -> 0.052304778 | F14: =IF(AND(G14="Interior calendar month",G13="Interior calendar month"),E14,"") -> 0.052304778 | G14: Interior calendar month | I14: 40756 | J14: 724216.5 | K14: 1339
A15: 40787 | B15: 1028320.4 | C15: 1818 | D15: =ROUND(B15/C15,2) -> 565.63 | E15: =IFERROR(B15/B14-1,"") -> 0.41990742 | F15: =IF(AND(G15="Interior calendar month",G14="Interior calendar month"),E15,"") -> 0.41990742 | G15: Interior calendar month | I15: 40787 | J15: 1028320.4 | K15: 1818
A16: 40817 | B16: 1103314.2 | C16: 2005 | D16: =ROUND(B16/C16,2) -> 550.28 | E16: =IFERROR(B16/B15-1,"") -> 0.072928507 | F16: =IF(AND(G16="Interior calendar month",G15="Interior calendar month"),E16,"") -> 0.072928507 | G16: Interior calendar month | I16: 40817 | J16: 1103314.2 | K16: 2005
A17: 40848 | B17: 1452116 | C17: 2751 | D17: =ROUND(B17/C17,2) -> 527.85 | E17: =IFERROR(B17/B16-1,"") -> 0.31613997 | F17: =IF(AND(G17="Interior calendar month",G16="Interior calendar month"),E17,"") -> 0.31613997 | G17: Interior calendar month | I17: 40848 | J17: 1452116 | K17: 2751
A18: 40878 | B18: 614490.92 | C18: 816 | D18: =ROUND(B18/C18,2) -> 753.05 | E18: =IFERROR(B18/B17-1,"") -> -0.57683069 | F18: =IF(AND(G18="Interior calendar month",G17="Interior calendar month"),E18,"") | G18: PARTIAL - through 09 Dec 2011 | I18: 40878 | J18: 614490.92 | K18: 816
I19: Grand Total | J19: 10247219 | K19: 19773
A20: Full-dataset total | B20: =SUM(B6:B18) -> 10247219 | C20: =SUM(C6:C18) -> 19773

Sheet Top Products
A1: Top Products
A3: Separate top tens from the verified Python/MariaDB results. Exact StockCode is the key; descriptions are observed labels, not categories.
A5: Rank | B5: StockCode | C5: Description | D5: Units sold | E5: Revenue GBP
A6: 1 | B6: 22423 | C6: REGENCY CAKESTAND 3 TIER | D6: 13851 | E6: 174156.54
A7: 2 | B7: 23843 | C7: PAPER CRAFT , LITTLE BIRDIE | D7: 80995 | E7: 168469.6
A8: 3 | B8: 85123A | C8: CREAM HANGING HEART T-LIGHT HOLDER | D8: 37641 | E8: 104462.75
A9: 4 | B9: 47566 | C9: PARTY BUNTING | D9: 18283 | E9: 99445.23
A10: 5 | B10: 85099B | C10: JUMBO BAG RED RETROSPOT | D10: 48371 | E10: 94159.81
A11: 6 | B11: 23166 | C11: MEDIUM CERAMIC TOP STORAGE JAR | D11: 78033 | E11: 81700.92
A12: 7 | B12: 23084 | C12: RABBIT NIGHT LIGHT | D12: 30739 | E12: 66870.03
A13: 8 | B13: 22086 | C13: PAPER CHAIN KIT 50'S CHRISTMAS | D13: 19329 | E13: 64875.59
A14: 9 | B14: 84879 | C14: ASSORTED COLOUR BIRD ORNAMENT | D14: 36362 | E14: 58927.62
A15: 10 | B15: 79321 | C15: CHILLI LIGHTS | D15: 10302 | E15: 54096.36
A23: Rank | B23: StockCode | C23: Description | D23: Units sold | E23: Revenue GBP
A24: 1 | B24: 23843 | C24: PAPER CRAFT , LITTLE BIRDIE | D24: 80995 | E24: 168469.6
A25: 2 | B25: 23166 | C25: MEDIUM CERAMIC TOP STORAGE JAR | D25: 78033 | E25: 81700.92
A26: 3 | B26: 22197 | C26: POPCORN HOLDER | D26: 56898 | E26: 51334.47
A27: 4 | B27: 84077 | C27: WORLD WAR 2 GLIDERS ASSTD DESIGNS | D27: 54951 | E27: 13814.01
A28: 5 | B28: 85099B | C28: JUMBO BAG RED RETROSPOT | D28: 48371 | E28: 94159.81
A29: 6 | B29: 85123A | C29: CREAM HANGING HEART T-LIGHT HOLDER | D29: 37641 | E29: 104462.75
A30: 7 | B30: 21212 | C30: PACK OF 72 RETROSPOT CAKE CASES | D30: 36396 | E30: 21246.45
A31: 8 | B31: 84879 | C31: ASSORTED COLOUR BIRD ORNAMENT | D31: 36362 | E31: 58927.62
A32: 9 | B32: 23084 | C32: RABBIT NIGHT LIGHT | D32: 30739 | E32: 66870.03
A33: 10 | B33: 22492 | C33: MINI PAINT SET VINTAGE | D33: 26633 | E33: 16937.82

Sheet Country Performance
A1: Country Performance
I2: Native PivotTable: country summary
A3: All countries remain in the table. Chart excludes the UK so smaller markets are readable; the title states this explicitly. Anonymous sales remain included.
A5: Country | B5: Revenue GBP | C5: Completed orders | D5: AOV GBP | E5: Revenue share | I5: Country | J5: Revenue GBP (sum) | K5: Completed orders (sum)
A6: United Kingdom | B6: 8724443.7 | C6: 17901 | D6: =ROUND(B6/C6,2) -> 487.37 | E6: =B6/Overview!$B$7 -> 0.85139621 | I6: United Kingdom | J6: 8724443.7 | K6: 17901
A7: Netherlands | B7: 283889.34 | C7: 93 | D7: =ROUND(B7/C7,2) -> 3052.57 | E7: =B7/Overview!$B$7 -> 0.027704037 | I7: Netherlands | J7: 283889.34 | K7: 93
A8: EIRE | B8: 270850.86 | C8: 282 | D8: =ROUND(B8/C8,2) -> 960.46 | E8: =B8/Overview!$B$7 -> 0.026431645 | I8: EIRE | J8: 270850.86 | K8: 282
A9: Germany | B9: 205381.15 | C9: 443 | D9: =ROUND(B9/C9,2) -> 463.61 | E9: =B9/Overview!$B$7 -> 0.020042623 | I9: Germany | J9: 205381.15 | K9: 443
A10: France | B10: 184493 | C10: 382 | D10: =ROUND(B10/C10,2) -> 482.97 | E10: =B10/Overview!$B$7 -> 0.018004201 | I10: France | J10: 184493 | K10: 382
A11: Australia | B11: 138103.81 | C11: 56 | D11: =ROUND(B11/C11,2) -> 2466.14 | E11: =B11/Overview!$B$7 -> 0.013477199 | I11: Australia | J11: 138103.81 | K11: 56
A12: Spain | B12: 55706.56 | C12: 88 | D12: =ROUND(B12/C12,2) -> 633.03 | E12: =B12/Overview!$B$7 -> 0.0054362611 | I12: Spain | J12: 55706.56 | K12: 88
A13: Switzerland | B13: 53065.6 | C13: 50 | D13: =ROUND(B13/C13,2) -> 1061.31 | E13: =B13/Overview!$B$7 -> 0.0051785366 | I13: Switzerland | J13: 53065.6 | K13: 50
A14: Japan | B14: 37416.37 | C14: 19 | D14: =ROUND(B14/C14,2) -> 1969.28 | E14: =B14/Overview!$B$7 -> 0.0036513681 | I14: Japan | J14: 37416.37 | K14: 19
A15: Belgium | B15: 36927.34 | C15: 98 | D15: =ROUND(B15/C15,2) -> 376.81 | E15: =B15/Overview!$B$7 -> 0.0036036449 | I15: Belgium | J15: 36927.34 | K15: 98
A16: Sweden | B16: 36828.83 | C16: 34 | D16: =ROUND(B16/C16,2) -> 1083.2 | E16: =B16/Overview!$B$7 -> 0.0035940316 | I16: Sweden | J16: 36828.83 | K16: 34
A17: Norway | B17: 32454.64 | C17: 32 | D17: =ROUND(B17/C17,2) -> 1014.21 | E17: =B17/Overview!$B$7 -> 0.0031671655 | I17: Norway | J17: 32454.64 | K17: 32
... A43: Saudi Arabia | B43: 145.92 | C43: 1 | D43: =ROUND(B43/C43,2) -> 145.92 | E43: =B43/Overview!$B$7 -> 1.4239961e-05 | I43: Saudi Arabia | J43: 145.92 | K43: 1
I44: Grand Total | J44: 10247219 | K44: 19773

Sheet Customer Analysis
A1: Customer Analysis
A3: Repeat customer = known ID with at least two distinct completed invoices in this observation window. Anonymous sales are not one fabricated customer.
A5: Customer metric | B5: Value | C5: Definition
A6: Known customers | B6: =B7 -> 4334 | C6: Distinct nonmissing eligible CustomerID
A7: Known-customer denominator | B7: 4334 | C7: Known customers with at least one completed order
A8: Repeat customers | B8: 2829 | C8: At least two distinct completed invoices
A9: One-order customers | B9: 1505 | C9: Exactly one completed invoice
A10: Repeat-customer rate | B10: =B8/B7 -> 0.65274573 | C10: Repeat customers / known-customer denominator
A11: Known-customer orders | B11: 18402 | C11: Distinct eligible invoices for known IDs
A12: Known-customer revenue GBP | B12: 8737227.6 | C12: Anonymous sales excluded only from this customer metric
A13: Eligible anonymous lines | B13: 131387 | C13: Remain in overall sales and orders
A16: Purchase frequency of known customers
A18: Completed-order band | B18: Known customers | C18: Share of known IDs | D18: Revenue GBP | E18: Completed orders
A19: 1 order | B19: 1505 | C19: =B19/$B$7 -> 0.34725427 | D19: 626605.9 | E19: 1505
A20: 2 orders | B20: 831 | C20: =B20/$B$7 -> 0.19173973 | D20: 720890.58 | E20: 1662
A21: 3-4 orders | B21: 897 | C21: =B21/$B$7 -> 0.20696816 | D21: 1197610.2 | E21: 3086
A22: 5-9 orders | B22: 715 | C22: =B22/$B$7 -> 0.16497462 | D22: 1728732.6 | E22: 4596
A23: 10+ orders | B23: 386 | C23: =B23/$B$7 -> 0.089063221 | D23: 4463388.3 | E23: 7553
A25: Reconciled known IDs | B25: =SUM(B19:B23) -> 4334
A28: The rate is 2,829 / 4,334 = 65.27% after display rounding. It is not lifetime retention, a cohort retention rate or a causal effect.
A30: Frequency bands are derived solely from each known customer's verified distinct completed-order count. No product categories or customer identities were inferred.

Sheet Data Quality
A1: Data Quality
A3: Sequential rule exclusions are disjoint; issue flags overlap. Signed excluded line values are not lost revenue or net returns.
A5: First applicable exclusion rule | B5: Before rows | C5: Excluded rows | D5: After rows | E5: Signed value GBP | F5: Absolute value GBP
A6: invalid_required_fields | B6: 541909 | C6: 0 | D6: 541909 | E6: 0 | F6: 0
A7: cancellation | B7: 541909 | C7: 9288 | D7: 532621 | E7: -896812.49 | F7: 896812.49
A8: nonpositive_quantity | B8: 532621 | C8: 1336 | D8: 531285 | E8: 0 | F8: 0
A9: nonpositive_price | B9: 531285 | C9: 1181 | D9: 530104 | E9: -22124.12 | F9: 22124.12
A10: nonproduct_or_unreviewed_code | B10: 530104 | C10: 2343 | D10: 527761 | E10: 395251.48 | F10: 395251.48
A11: exact_duplicate_extra | B11: 527761 | C11: 5221 | D11: 522540 | E11: 24213.74 | F11: 24213.74
A13: Total excluded lines | C13: =SUM(C6:C11) -> 19369
A16: Overlapping issue / retained group | B16: Lines | C16: Share of denominator | D16: Denominator / interpretation
A17: Raw lines missing CustomerID | B17: 135080 | C17: =B17/Sources!$B$28 -> 0.24926694 | D17: All 541,909 source lines
A18: Eligible anonymous lines | B18: 131387 | C18: =B18/Sources!$B$29 -> 0.25143912 | D18: All 522,540 eligible lines
A19: Missing descriptions | B19: 1454 | C19: =B19/Sources!$B$28 -> 0.0026831073 | D19: All source lines
A20: Cancellation lines | B20: 9288 | C20: =B20/Sources!$B$28 -> 0.017139409 | D20: All source lines
A21: Negative quantities | B21: 10624 | C21: =B21/Sources!$B$28 -> 0.019604768 | D21: All source lines
A22: Nonpositive prices | B22: 2517 | C22: =B22/Sources!$B$28 -> 0.0046446913 | D22: All source lines
A23: Exact duplicate extras (source) | B23: 5268 | C23: =B23/Sources!$B$28 -> 0.0097211894 | D23: All source lines; overlaps earlier exclusions
A24: Conversion failures | B24: 0 | C24: =B24/Sources!$B$28 -> 0 | D24: Actual conversions; zero for this input
A27: Limitations and interpretation
A28: Completed-sales revenue is not net revenue or profit. Cancellations, negative adjustments, nonpositive prices and reviewed non-product items are excluded.
A29: 5,268 source duplicate extras were flagged. The final duplicate rule removed 5,221 otherwise eligible lines worth GBP 24,213.74; 47 extras had already been excluded by earlier rules.
A30: Exact-duplicate removal is an assumption: identical lines can be legitimate. InvoiceNo is never deduplicated by itself. The source workbook is unchanged.
A31: Missing customer IDs restrict customer metrics but do not invalidate sales. Do not fill all unknown IDs with one customer. Missing descriptions alone do not invalidate recognized merchandise.
A32: Dec 2010: starts day 1 but completeness unverified. Dec 2011: partial through 9 Dec. Do not compare boundary months with full months without qualification.
A33: Case-distinct product codes remain separate. Large transactions remain and may affect rankings. Descriptions vary; no categories, costs, profit, return-to-sale matches or causal explanations are invented.

Sheet Sources
A1: Sources
A3: Traceable snapshot of verified Python outputs and MariaDB reconciliation. No cleaning rules were changed.
A5: Dataset attribution and analytical lineage
A6: Chen, D. (2015). Online Retail [Dataset]. UCI Machine Learning Repository.
A7: Dataset: https://archive.ics.uci.edu/dataset/352/online+retail
A8: DOI: https://doi.org/10.24432/C5BW33 | License: https://creativecommons.org/licenses/by/4.0/
A9: CC BY 4.0: give credit, link the license, indicate modifications and do not imply endorsement. Cleaning and aggregation are project modifications.
A10: Observed coverage: 01 Dec 2010 08:26 to 09 Dec 2011 12:50. Dec 2010 begins on day 1 but completeness is unverified; Dec 2011 is partial.
A11: Analysis input: reports/analysis_20261017T165141_531793Z
A12: Cleaning evidence: reports/cleaning_20261017T165110_899648Z/cleaning_summary.json
A13: MariaDB 10.4.32: all seven equivalent SQL tables matched Python. See reports/sql_reconciliation.md.
A14: Cleaned input SHA-256: 094fbf634055c2cd3f6410cf0ebaff28948c24cee62ccba7461d4d0f73bb202a
... A16: Historical analysis files may say SQL was unexecuted at generation; the later SQL reconciliation report is the current evidence.
A19: Verified reference metric | B19: Python value | C19: Unit / role
A20: Revenue GBP | B20: 10247219 | C20: GBP
A21: Completed orders | B21: 19773 | C21: Count
A22: Units sold | B22: 5561387 | C22: Count
A23: Average order value GBP | B23: 518.24 | C23: GBP
A24: Known customers | B24: 4334 | C24: Count
A25: Repeat customers | B25: 2829 | C25: Count
A26: Repeat rate (rounded reference) | B26: 0.6527 | C26: Rate
A27: Retained missing-customer lines | B27: 131387 | C27: Count
A28: Raw rows | B28: 541909 | C28: Count
A29: Completed-sales rows | B29: 522540 | C29: Count
A30: Excluded rows | B30: 19369 | C30: Count
A33: Regenerate and refresh
A34: From the project root: .\.venv\Scripts\python.exe src/build_excel.py
A35: To regenerate an existing workbook safely: .\.venv\Scripts\python.exe src/build_excel.py --replace
A36: The --replace option archives the existing workbook before replacement. Requirements: Python environment plus installed Windows Microsoft Excel for calculation, native pivots and preview export.
A37: For a new verified analysis: pass --analysis reports/ANALYSIS_RUN and --sql-evidence reports/SQL_RECONCILIATION.json. They must refer to the same data.
A38: Refresh All updates embedded PivotTable caches only. It does not rerun Python or fetch CSV changes. Regenerate to replace the snapshot and rerun validation.
A39: Summary table filters and PivotTable filters do not recalculate the full-dataset Overview cards. Charts reference their nearby summary data; restore filters before reconciliation.
A40: See reports/excel_refresh_and_pivottables.md for exact transaction-level Power Query/Data Model steps. Distinct invoices are essential: ordinary Count of invoice lines is not order count.
A43: Native PivotTables and manual recreation
A44: Native Excel PivotTables created: MonthlySalesPivot (Monthly Sales!I5) and CountrySalesPivot (Country Performance!I5). Both summarize embedded verified aggregate rows, not transaction-level facts.
A45: Manual monthly pivot: click MonthlySummary > Insert > PivotTable > Existing Worksheet > Monthly Sales!I5. Rows = Month; Values = Sum of Revenue GBP and Sum of Completed orders; format month as mmm yyyy and GBP with two decimals.
A46: Manual country pivot: click CountrySummary > Insert > PivotTable > Existing Worksheet > Country Performance!I5. Rows = Country; Values = Sum of Revenue GBP and Sum of Completed orders; format GBP, sort revenue descending.
... A49: Repeat rate denominator: all known IDs with eligible sales in this observation window. Anonymous sales remain in overall sales and are excluded only from customer-specific measures.
